placeholder-1.5.dist-info/WHEEL
placeholder-1.5.dist-info/LICENSE.txt
placeholder-1.5.dist-info/RECORD
placeholder-1.5.dist-info/top_level.txt
placeholder-1.5.dist-info/METADATA
placeholder/py.typed
placeholder/__init__.py
placeholder/partials.c
placeholder/partials.abi3.so
