Metadata-Version: 2.1
Name: placeholder
Version: 1.5
Summary: Operator overloading for fast anonymous functions.
Author-email: Aric Coady <aric.coady@gmail.com>
License: Copyright 2022 Aric Coady
Project-URL: Homepage, https://github.com/coady/placeholder
Project-URL: Documentation, https://coady.github.io/placeholder
Project-URL: Changelog, https://github.com/coady/placeholder/blob/main/CHANGELOG.md
Project-URL: Issues, https://github.com/coady/placeholder/issues
Keywords: functional,lambda,scala,underscore
Classifier: Development Status :: 5 - Production/Stable
Classifier: Intended Audience :: Developers
Classifier: License :: OSI Approved :: Apache Software License
Classifier: Operating System :: OS Independent
Classifier: Programming Language :: Python :: 3
Classifier: Programming Language :: Python :: 3.8
Classifier: Programming Language :: Python :: 3.9
Classifier: Programming Language :: Python :: 3.10
Classifier: Programming Language :: Python :: 3.11
Classifier: Programming Language :: Python :: 3.12
Classifier: Programming Language :: Python :: 3.13
Classifier: Topic :: Software Development :: Libraries :: Python Modules
Classifier: Typing :: Typed
Requires-Python: >=3.8
License-File: LICENSE.txt
